fd_dj_accounts/__init__.py
fd_dj_accounts/apps.py
fd_dj_accounts/auth_backends.py
fd_dj_accounts/base_models.py
fd_dj_accounts/models.py
fd_dj_accounts/py.typed
fd_dj_accounts/urls.py
fd_dj_accounts/views.py
fd_dj_accounts/migrations/0001_initial.py
fd_dj_accounts/migrations/__init__.py
fyndata_django_accounts-0.15.0.dist-info/licenses/LICENSE
fyndata_django_accounts-0.15.0.dist-info/METADATA
fyndata_django_accounts-0.15.0.dist-info/WHEEL
fyndata_django_accounts-0.15.0.dist-info/top_level.txt
fyndata_django_accounts-0.15.0.dist-info/RECORD
