Metadata-Version: 2.4
Name: fyndata-django-accounts
Version: 0.15.0
Summary: Reusable Django app to replace the default Django user (account) model.
Author-email: "Fyndata (Fynpal SpA)" <no-reply@fyndata.com>
License-Expression: MIT
Project-URL: Homepage, https://github.com/fyndata/fyndata-django-accounts
Project-URL: Changelog, https://github.com/fyndata/fyndata-django-accounts/blob/develop/HISTORY.rst
Keywords: fyndata-django-accounts
Classifier: Development Status :: 3 - Alpha
Classifier: Framework :: Django :: 4.2
Classifier: Intended Audience :: Developers
Classifier: Natural Language :: English
Classifier: Programming Language :: Python :: 3
Classifier: Programming Language :: Python :: 3.9
Classifier: Programming Language :: Python :: 3.10
Requires-Python: >=3.9
License-File: LICENSE
Requires-Dist: Django>=4.2
Dynamic: license-file
